capexplain/__init__.py
capexplain/cape.py
capexplain/utils.py
capexplain/cl/__init__.py
capexplain/cl/cfgoption.py
capexplain/cl/command.py
capexplain/cl/instrumentation.py
capexplain/database/__init__.py
capexplain/database/dbaccess.py
capexplain/explain/__init__.py
capexplain/explain/explanation.py
capexplain/explain/explanation_crime.py
capexplain/explain/explanation_old.py
capexplain/explain/explanation_with_db.py
capexplain/explain/find_lambda_with_uq.py
capexplain/explain/pattern_retrieval.py
capexplain/explain/tuple_retrieval.py
capexplain/explanation_model/__init__.py
capexplain/explanation_model/explanation_model.py
capexplain/fd/__init__.py
capexplain/fd/fd.py
capexplain/gui/Cape_GUI.py
capexplain/gui/DBinfo.py
capexplain/gui/Exp_Frame.py
capexplain/gui/Pattern_Frame.py
capexplain/gui/Plotting.py
capexplain/gui/Profiler.py
capexplain/gui/User_Query_Frame.py
capexplain/gui/__init__.py
capexplain/gui/label.py
capexplain/gui/test.py
capexplain/gui/test1.py
capexplain/gui/test_exp.py
capexplain/pattern_miner/PatternMiner.py
capexplain/pattern_miner/__init__.py
capexplain/pattern_miner/permtest.py
capexplain/pattern_model/LocalRegressionPattern.py
capexplain/pattern_model/PatternCollection.py
capexplain/pattern_model/__init__.py
capexplain/similarity/__init__.py
capexplain/similarity/category_embedding.py
capexplain/similarity/category_network_embedding.py
capexplain/similarity/category_similarity_matrix.py
capexplain/similarity/category_similarity_naive.py
capexplain-0.4.dist-info/LICENSE.txt
capexplain-0.4.dist-info/METADATA
capexplain-0.4.dist-info/WHEEL
capexplain-0.4.dist-info/entry_points.txt
capexplain-0.4.dist-info/top_level.txt
capexplain-0.4.dist-info/RECORD
