Metadata-Version: 2.1
Name: capexplain
Version: 0.4
Summary: Cape - a system for explaining outliers in aggregation results through counterbalancing.
Home-page: https://github.com/iitdbgroup/cape
Author: US <e@g.com>
Author-email: who@gmail.com
License: Apache2
Keywords: db
Platform: any
Classifier: Programming Language :: Python
Classifier: Development Status :: 4 - Beta
Classifier: Environment :: Console
Classifier: License :: OSI Approved :: Apache Software License
Classifier: Operating System :: OS Independent
Classifier: Intended Audience :: End Users/Desktop
Classifier: Intended Audience :: Developers
Classifier: Topic :: Scientific/Engineering :: Information Analysis
Requires-Dist: certifi (>=2018.4.16)
Requires-Dist: chardet (>=3.0.4)
Requires-Dist: colorful (>=0.4.1)
Requires-Dist: geopy
Requires-Dist: idna (>=2.7)
Requires-Dist: matplotlib (==3.0.2)
Requires-Dist: numpy (>=1.14.5)
Requires-Dist: pandas (==0.23.4)
Requires-Dist: patsy (>=0.5.0)
Requires-Dist: pkginfo (>=1.4.2)
Requires-Dist: psycopg2-binary (>=2.7.6)
Requires-Dist: python-dateutil (>=2.7.3)
Requires-Dist: pytz (>=2018.5)
Requires-Dist: requests (>=2.19.1)
Requires-Dist: requests-toolbelt (>=0.8.0)
Requires-Dist: scikit-learn (>=0.19.2)
Requires-Dist: scipy (==1.2.1)
Requires-Dist: six (>=1.11.0)
Requires-Dist: sklearn (>=0.0)
Requires-Dist: SQLAlchemy (==1.2.10)
Requires-Dist: statsmodels (>=0.9.0)
Requires-Dist: tqdm (>=4.23.4)
Requires-Dist: urllib3 (<1.24,>=1.23)
Requires-Dist: pandastable (>=0.12.0)
Requires-Dist: matplotlib (>=3.0.2)
